Workbook

Sheet Quotation
B3: Offered Party | C3: ${offerValidation.DISTRIBUTORNAME} | J3: Selling Company | K3: =Settings!A11 -> ${offerValidation.SELLINGCOMPANY}
B4: Address | C4: =Settings!A13 -> ${offerValidation.DISTRIBUTORADDRESS} | J4: Address
B7: Quotation Request Information
B8: FAST Request ID | I8: Material Group | O8: Requestor Name
B9: Customer ID | D9: =Settings!A14 -> ${offerValidation.CUSTOMER_CODE} | I9: Offer Approval Date | K9: ${offerValidation.OFFERDATE} | O9: Contact Information
B10: Customer Name | I10: Offer Validity | K10: ${offerValidation.OFFERVALIDITY} | O10: Bayer Representative
B11: Shipment Terms | D11: =Settings!A12 -> ${offerValidation.DISTRIBUTORNAME} | I11: Payment Terms | K11: =Settings!A7 -> ${offerValidation.PAYMENTTERMS} | O11: Contact Information
B12: Delivery Terms | D12: =Settings!A8 -> ${offerValidation.DELIVERYTERMS}
B14: Price Quotation
B15: No. | C15: Material Code | D15: Product Name | G15: Product Generic Name | J15: Offer QTY /UoM | M15: Pack Factor | O15: Unit Dosge | P15: MSP | R15: FOC/ Discount | S15: NSP
P17: excl. vat. | Q17: incl. vat. | S17: excl. vat. | T17: incl. vat.
B18: 1 | C18: ${table:offerProductValidation.SKU} | D18: ${table:offerProductValidation.PRODUCTNAME} | J18: ${table:offerProductValidation.PAID_VOLUME} / ${table:offerProductValidation.UNIT} | M18: ${table:offerProductValidation.PACKSIZE} | R18: ${table:offerProductValidation.FOC}
B19: 2
B20: 3
B22: Product Offer Information
B23: No. | C23: Material Code | E23: Offer Pack Description | F23: TPU | G23: GPU | H23: THCC (24 Digit Code) | K23: Manufacturer | M23: Country of Origin
B26: 1
B27: 2
B28: 3
B30: Customer Request Information | H30: Quotation Delivery Channels | J30: Receiver Information (Name, Phone, Address and/or Email)
B31: Quotation Date (วันที่) | H31: DKSH Quotation Office
B32: Attention to (เรียน) | H32: Send to Bayer
B33: Validity Period (กำหนดยืนราคา) | F33: years (ปี) | H33: Email/ Fax
B34: Delivery Due (กำหนดส่งสินค้า) | F34: years (ปี) | H34: Send to Customer
B37: Remarks
B38: With reference to the above tender, you must not on-sell the above mentioned products at a price higher than those listed above. However, you are always free to sell at a price lower, at your discretion.
I42: Approved by | K42: Name
K43: Position

Sheet Settings
A1: Header fields | B1: Description
A2: ${offerValidation.OFFERID} | B2: Contract Number
A3: ${offerValidation.TENDERID} | B3: Tender Reference
A4: ${offerValidation.OFFERDATE} | B4: Offer Date
A5: ${offerValidation.OFFERVALIDITY} | B5: Offer Validity
A6: ${offerValidation.SHIPMENTTERMS} | B6: Shipment Terms
A7: ${offerValidation.PAYMENTTERMS} | B7: Payment Terms
A8: ${offerValidation.DELIVERYTERMS} | B8: Delivery Terms
A9: ${offerValidation.INSTITUTENAME} | B9: Offer Party
A10: ${offerValidation.PROCUREMENT_REASON} | B10: Procurement reason
A11: ${offerValidation.SELLINGCOMPANY} | B11: Selling Company
A12: ${offerValidation.DISTRIBUTORNAME} | B12: Offered Party
... A14: ${offerValidation.CUSTOMER_CODE} | B14: Customer ID
A16: Product table fields
A17: SKU CODE | B17: Article name | C17: PAID VOLUME | D17: UNIT | E17: OFFER PRICE | F17: CURRENCY | G17: OFFER_PRICE_VAT | H17: GROSS SALES OFFER CURRENCY | I17: GROSS_SALES_OFFER_CURRENCY_VAT | J17: OFFER_ID | K17: SORTER | L17: Pack Factor | M17: Samples | N17: Origin | O17: FOC | P17: Total Quantity Units | Q17: Total QTY | R17: Net Price | S17: Amount in numbers | T17: VAT total | U17: Amount in numbers vat
A18: ${table:offerProductValidation.SKU} | B18: ${table:offerProductValidation.PRODUCTNAME} | C18: ${table:offerProductValidation.PAID_VOLUME} | D18: ${table:offerProductValidation.UNIT} | E18: ${table:offerProductValidation.OFFER_PRICE} | F18: ${table:offerProductValidation.CURRENCY} | G18: ${table:offerProductValidation.OFFER_PRICE_VAT} | H18: ${table:offerProductValidation.GROSS_SALES_OFFER_CURRENCY} | I18: ${table:offerProductValidation.GROSS_SALES_OFFER_CURRENCY_VAT} | J18: ${table:offerProductValidation.OFFER_ID} | K18: ${table:offerProductValidation.SORTER} | L18: ${table:offerProductValidation.PACKSIZE} | M18: ${table:offerProductValidation.SAMPLES} | N18: ${table:offerProductValidation.COUNTRYOFORIGIN} | O18: ${table:offerProductValidation.FOC} | P18: ${table:offerProductValidation.TOTAL_QUANTITY_UNITS} | Q18: =IF(D18>0,IF(D18="Unit",CONCATENATE(Settings!P18," ",Settings!D18,"s"),CONCATENATE((Settings!P18/Settings!L18)," ",Settings!D18,"s")),"") -> #VALUE! | R18: ${table:offerProductValidation.NET_PRICE} | S18: ${offerValidation.AMOUNT_IN_NUMBERS} | T18: ${offerValidation.VAT_TOTAL} | U18: ${offerValidation.AMOUNT_IN_NUMBERS_VAT}
Q19: =IF(D19>0,IF(D19="Unit",CONCATENATE(Settings!P19," ",Settings!D19,"s"),CONCATENATE((Settings!P19/Settings!L19)," ",Settings!D19,"s")),"")
Q20: =IF(D20>0,IF(D20="Unit",CONCATENATE(Settings!P20," ",Settings!D20,"s"),CONCATENATE((Settings!P20/Settings!L20)," ",Settings!D20,"s")),"")
Q21: =IF(D21>0,IF(D21="Unit",CONCATENATE(Settings!P21," ",Settings!D21,"s"),CONCATENATE((Settings!P21/Settings!L21)," ",Settings!D21,"s")),"")
Q22: =IF(D22>0,IF(D22="Unit",CONCATENATE(Settings!P22," ",Settings!D22,"s"),CONCATENATE((Settings!P22/Settings!L22)," ",Settings!D22,"s")),"")
Q23: =IF(D23>0,IF(D23="Unit",CONCATENATE(Settings!P23," ",Settings!D23,"s"),CONCATENATE((Settings!P23/Settings!L23)," ",Settings!D23,"s")),"")
Q24: =IF(D24>0,IF(D24="Unit",CONCATENATE(Settings!P24," ",Settings!D24,"s"),CONCATENATE((Settings!P24/Settings!L24)," ",Settings!D24,"s")),"")
Q25: =IF(D25>0,IF(D25="Unit",CONCATENATE(Settings!P25," ",Settings!D25,"s"),CONCATENATE((Settings!P25/Settings!L25)," ",Settings!D25,"s")),"")
Q26: =IF(D26>0,IF(D26="Unit",CONCATENATE(Settings!P26," ",Settings!D26,"s"),CONCATENATE((Settings!P26/Settings!L26)," ",Settings!D26,"s")),"")
Q27: =IF(D27>0,IF(D27="Unit",CONCATENATE(Settings!P27," ",Settings!D27,"s"),CONCATENATE((Settings!P27/Settings!L27)," ",Settings!D27,"s")),"")
Q28: =IF(D28>0,IF(D28="Unit",CONCATENATE(Settings!P28," ",Settings!D28,"s"),CONCATENATE((Settings!P28/Settings!L28)," ",Settings!D28,"s")),"")
Q29: =IF(D29>0,IF(D29="Unit",CONCATENATE(Settings!P29," ",Settings!D29,"s"),CONCATENATE((Settings!P29/Settings!L29)," ",Settings!D29,"s")),"")
Q30: =IF(D30>0,IF(D30="Unit",CONCATENATE(Settings!P30," ",Settings!D30,"s"),CONCATENATE((Settings!P30/Settings!L30)," ",Settings!D30,"s")),"")
... Q52: =IF(D52>0,IF(D52="Unit",CONCATENATE(Settings!P52," ",Settings!D52,"s"),CONCATENATE((Settings!P52/Settings!L52)," ",Settings!D52,"s")),"")
