Workbook

Sheet Quotation
C3: Offer Party | D3: =Settings!A9 -> ${offerValidation.INSTITUTENAME}
C5: Procurement Method | D5: =Settings!A10 -> ${offerValidation.PROCUREMENT_REASON}
C7: Contract Number | F7: Tender Reference | I7: Offer Date | L7: Offer Validity
C8: =Settings!A2 -> ${offerValidation.OFFERID} | F8: =Settings!A3 -> ${offerValidation.TENDERID} | I8: =Settings!A4 -> ${offerValidation.OFFERDATE} | L8: =Settings!A5 -> ${offerValidation.OFFERVALIDITY}
C10: Shipment Terms | F10: Payment Terms | I10: Delivery Terms
C11: =Settings!A6 -> ${offerValidation.SHIPMENTTERMS} | F11: =Settings!A7 -> ${offerValidation.PAYMENTTERMS} | I11: =Settings!A8 -> ${offerValidation.DELIVERYTERMS}
D13: Article Name | E13: Qty | F13: Pack Factor | G13: MSP | H13: MSP with VAT | I13: Total | J13: Total with VAT | L13: Samples | M13: Origin | N13: Contract ID | O13: FOC | P13: Total Qty | Q13: NSP
C14: =IF(Settings!A18="","",Settings!A18) -> ${table:offerProductValidation.SKU} | D14: =IF(Settings!B18="","",Settings!B18) -> ${table:offerProductValidation.PRODUCT_UNIT_NAME} | E14: =IF(CONCATENATE(Settings!C18," ",Settings!D18,"s")=" s"," ",CONCATENATE(Settings!C18," ",Settings!D18,"s")) -> ${table:offerProductValidation.PAID_VOLUME} ${table:offerProductValidation.UNIT}s | F14: =IF(Settings!L18="","",Settings!L18) -> ${table:offerProductValidation.PACKSIZE} | G14: =CONCATENATE(Settings!E18," ",Settings!F18) -> ${table:offerProductValidation.OFFER_PRICE} ${table:offerProductValidation.CURRENCY} | H14: =CONCATENATE(Settings!G18," ",Settings!F18) -> ${table:offerProductValidation.OFFER_PRICE_VAT} ${table:offerProductValidation.CURRENCY} | I14: =CONCATENATE(Settings!H18," ",Settings!F18) -> ${table:offerProductValidation.GROSS_SALES_OFFER_CURRENCY} ${table:offerProductValidation.CURRENCY} | J14: =CONCATENATE(Settings!I18," ",Settings!F18) -> ${table:offerProductValidation.GROSS_SALES_OFFER_CURRENCY_VAT} ${table:offerProductValidation.CURRENCY} | L14: =IF(Settings!M18="","",Settings!M18) -> ${table:offerProductValidation.SAMPLES} | M14: =IF(Settings!N18="","",Settings!N18) -> ${table:offerProductValidation.COUNTRYOFORIGIN} | N14: =IF(CONCATENATE(Settings!J18,"-",Settings!K18) = "-","",CONCATENATE(Settings!J18,"-",Settings!K18)) -> ${table:offerProductValidation.OFFER_ID}-${table:offerProductValidation.SORTER} | O14: =IF(Settings!O18="","",Settings!O18) -> ${table:offerProductValidation.FOC} | P14: =Settings!Q18 -> #VALUE! | Q14: =_xlfn.CONCAT(Settings!R18," ",Settings!F18) -> ${table:offerProductValidation.NET_PRICE} ${table:offerProductValidation.CURRENCY}
C15: =IF(Settings!A19="","",Settings!A19) | D15: =IF(Settings!B19="","",Settings!B19) | E15: =IF(CONCATENATE(Settings!C19," ",Settings!D19,"s")=" s"," ",CONCATENATE(Settings!C19," ",Settings!D19,"s")) | F15: =IF(Settings!L19="","",Settings!L19) | G15: =CONCATENATE(Settings!E19," ",Settings!F19) | H15: =CONCATENATE(Settings!G19," ",Settings!F19) | I15: =CONCATENATE(Settings!H19," ",Settings!F19) | J15: =CONCATENATE(Settings!I19," ",Settings!F19) | L15: =IF(Settings!M19="","",Settings!M19) | M15: =IF(Settings!N19="","",Settings!N19) | N15: =IF(CONCATENATE(Settings!J19,"-",Settings!K19) = "-","",CONCATENATE(Settings!J19,"-",Settings!K19)) | O15: =IF(Settings!O19="","",Settings!O19) | P15: =Settings!Q19 | Q15: =_xlfn.CONCAT(Settings!R19," ",Settings!F19)
C16: =IF(Settings!A20="","",Settings!A20) | D16: =IF(Settings!B20="","",Settings!B20) | E16: =IF(CONCATENATE(Settings!C20," ",Settings!D20,"s")=" s"," ",CONCATENATE(Settings!C20," ",Settings!D20,"s")) | F16: =IF(Settings!L20="","",Settings!L20) | G16: =CONCATENATE(Settings!E20," ",Settings!F20) | H16: =CONCATENATE(Settings!G20," ",Settings!F20) | I16: =CONCATENATE(Settings!H20," ",Settings!F20) | J16: =CONCATENATE(Settings!I20," ",Settings!F20) | L16: =IF(Settings!M20="","",Settings!M20) | M16: =IF(Settings!N20="","",Settings!N20) | N16: =IF(CONCATENATE(Settings!J20,"-",Settings!K20) = "-","",CONCATENATE(Settings!J20,"-",Settings!K20)) | O16: =IF(Settings!O20="","",Settings!O20) | P16: =Settings!Q20 | Q16: =_xlfn.CONCAT(Settings!R20," ",Settings!F20)
C17: =IF(Settings!A21="","",Settings!A21) | D17: =IF(Settings!B21="","",Settings!B21) | E17: =IF(CONCATENATE(Settings!C21," ",Settings!D21,"s")=" s"," ",CONCATENATE(Settings!C21," ",Settings!D21,"s")) | F17: =IF(Settings!L21="","",Settings!L21) | G17: =CONCATENATE(Settings!E21," ",Settings!F21) | H17: =CONCATENATE(Settings!G21," ",Settings!F21) | I17: =CONCATENATE(Settings!H21," ",Settings!F21) | J17: =CONCATENATE(Settings!I21," ",Settings!F21) | L17: =IF(Settings!M21="","",Settings!M21) | M17: =IF(Settings!N21="","",Settings!N21) | N17: =IF(CONCATENATE(Settings!J21,"-",Settings!K21) = "-","",CONCATENATE(Settings!J21,"-",Settings!K21)) | O17: =IF(Settings!O21="","",Settings!O21) | P17: =Settings!Q21 | Q17: =_xlfn.CONCAT(Settings!R21," ",Settings!F21)
C18: =IF(Settings!A22="","",Settings!A22) | D18: =IF(Settings!B22="","",Settings!B22) | E18: =IF(CONCATENATE(Settings!C22," ",Settings!D22,"s")=" s"," ",CONCATENATE(Settings!C22," ",Settings!D22,"s")) | F18: =IF(Settings!L22="","",Settings!L22) | G18: =CONCATENATE(Settings!E22," ",Settings!F22) | H18: =CONCATENATE(Settings!G22," ",Settings!F22) | I18: =CONCATENATE(Settings!H22," ",Settings!F22) | J18: =CONCATENATE(Settings!I22," ",Settings!F22) | L18: =IF(Settings!M22="","",Settings!M22) | M18: =IF(Settings!N22="","",Settings!N22) | N18: =IF(CONCATENATE(Settings!J22,"-",Settings!K22) = "-","",CONCATENATE(Settings!J22,"-",Settings!K22)) | O18: =IF(Settings!O22="","",Settings!O22) | P18: =Settings!Q22 | Q18: =_xlfn.CONCAT(Settings!R22," ",Settings!F22)
C19: =IF(Settings!A23="","",Settings!A23) | D19: =IF(Settings!B23="","",Settings!B23) | E19: =IF(CONCATENATE(Settings!C23," ",Settings!D23,"s")=" s"," ",CONCATENATE(Settings!C23," ",Settings!D23,"s")) | F19: =IF(Settings!L23="","",Settings!L23) | G19: =CONCATENATE(Settings!E23," ",Settings!F23) | H19: =CONCATENATE(Settings!G23," ",Settings!F23) | I19: =CONCATENATE(Settings!H23," ",Settings!F23) | J19: =CONCATENATE(Settings!I23," ",Settings!F23) | L19: =IF(Settings!M23="","",Settings!M23) | M19: =IF(Settings!N23="","",Settings!N23) | N19: =IF(CONCATENATE(Settings!J23,"-",Settings!K23) = "-","",CONCATENATE(Settings!J23,"-",Settings!K23)) | O19: =IF(Settings!O23="","",Settings!O23) | P19: =Settings!Q23 | Q19: =_xlfn.CONCAT(Settings!R23," ",Settings!F23)
C20: =IF(Settings!A24="","",Settings!A24) | D20: =IF(Settings!B24="","",Settings!B24) | E20: =IF(CONCATENATE(Settings!C24," ",Settings!D24,"s")=" s"," ",CONCATENATE(Settings!C24," ",Settings!D24,"s")) | F20: =IF(Settings!L24="","",Settings!L24) | G20: =CONCATENATE(Settings!E24," ",Settings!F24) | H20: =CONCATENATE(Settings!G24," ",Settings!F24) | I20: =CONCATENATE(Settings!H24," ",Settings!F24) | J20: =CONCATENATE(Settings!I24," ",Settings!F24) | L20: =IF(Settings!M24="","",Settings!M24) | M20: =IF(Settings!N24="","",Settings!N24) | N20: =IF(CONCATENATE(Settings!J24,"-",Settings!K24) = "-","",CONCATENATE(Settings!J24,"-",Settings!K24)) | O20: =IF(Settings!O24="","",Settings!O24) | P20: =Settings!Q24 | Q20: =_xlfn.CONCAT(Settings!R24," ",Settings!F24)
C21: =IF(Settings!A25="","",Settings!A25) | D21: =IF(Settings!B25="","",Settings!B25) | E21: =IF(CONCATENATE(Settings!C25," ",Settings!D25,"s")=" s"," ",CONCATENATE(Settings!C25," ",Settings!D25,"s")) | F21: =IF(Settings!L25="","",Settings!L25) | G21: =CONCATENATE(Settings!E25," ",Settings!F25) | H21: =CONCATENATE(Settings!G25," ",Settings!F25) | I21: =CONCATENATE(Settings!H25," ",Settings!F25) | J21: =CONCATENATE(Settings!I25," ",Settings!F25) | L21: =IF(Settings!M25="","",Settings!M25) | M21: =IF(Settings!N25="","",Settings!N25) | N21: =IF(CONCATENATE(Settings!J25,"-",Settings!K25) = "-","",CONCATENATE(Settings!J25,"-",Settings!K25)) | O21: =IF(Settings!O25="","",Settings!O25) | P21: =Settings!Q25 | Q21: =_xlfn.CONCAT(Settings!R25," ",Settings!F25)
C22: =IF(Settings!A26="","",Settings!A26) | D22: =IF(Settings!B26="","",Settings!B26) | E22: =IF(CONCATENATE(Settings!C26," ",Settings!D26,"s")=" s"," ",CONCATENATE(Settings!C26," ",Settings!D26,"s")) | F22: =IF(Settings!L26="","",Settings!L26) | G22: =CONCATENATE(Settings!E26," ",Settings!F26) | H22: =CONCATENATE(Settings!G26," ",Settings!F26) | I22: =CONCATENATE(Settings!H26," ",Settings!F26) | J22: =CONCATENATE(Settings!I26," ",Settings!F26) | L22: =IF(Settings!M26="","",Settings!M26) | M22: =IF(Settings!N26="","",Settings!N26) | N22: =IF(CONCATENATE(Settings!J26,"-",Settings!K26) = "-","",CONCATENATE(Settings!J26,"-",Settings!K26)) | O22: =IF(Settings!O26="","",Settings!O26) | P22: =Settings!Q26 | Q22: =_xlfn.CONCAT(Settings!R26," ",Settings!F26)
C23: =IF(Settings!A27="","",Settings!A27) | D23: =IF(Settings!B27="","",Settings!B27) | E23: =IF(CONCATENATE(Settings!C27," ",Settings!D27,"s")=" s"," ",CONCATENATE(Settings!C27," ",Settings!D27,"s")) | F23: =IF(Settings!L27="","",Settings!L27) | G23: =CONCATENATE(Settings!E27," ",Settings!F27) | H23: =CONCATENATE(Settings!G27," ",Settings!F27) | I23: =CONCATENATE(Settings!H27," ",Settings!F27) | J23: =CONCATENATE(Settings!I27," ",Settings!F27) | L23: =IF(Settings!M27="","",Settings!M27) | M23: =IF(Settings!N27="","",Settings!N27) | N23: =IF(CONCATENATE(Settings!J27,"-",Settings!K27) = "-","",CONCATENATE(Settings!J27,"-",Settings!K27)) | O23: =IF(Settings!O27="","",Settings!O27) | P23: =Settings!Q27 | Q23: =_xlfn.CONCAT(Settings!R27," ",Settings!F27)
C24: =IF(Settings!A28="","",Settings!A28) | D24: =IF(Settings!B28="","",Settings!B28) | E24: =IF(CONCATENATE(Settings!C28," ",Settings!D28,"s")=" s"," ",CONCATENATE(Settings!C28," ",Settings!D28,"s")) | F24: =IF(Settings!L28="","",Settings!L28) | G24: =CONCATENATE(Settings!E28," ",Settings!F28) | H24: =CONCATENATE(Settings!G28," ",Settings!F28) | I24: =CONCATENATE(Settings!H28," ",Settings!F28) | J24: =CONCATENATE(Settings!I28," ",Settings!F28) | L24: =IF(Settings!M28="","",Settings!M28) | M24: =IF(Settings!N28="","",Settings!N28) | N24: =IF(CONCATENATE(Settings!J28,"-",Settings!K28) = "-","",CONCATENATE(Settings!J28,"-",Settings!K28)) | O24: =IF(Settings!O28="","",Settings!O28) | P24: =Settings!Q28 | Q24: =_xlfn.CONCAT(Settings!R28," ",Settings!F28)
C25: =IF(Settings!A29="","",Settings!A29) | D25: =IF(Settings!B29="","",Settings!B29) | E25: =IF(CONCATENATE(Settings!C29," ",Settings!D29,"s")=" s"," ",CONCATENATE(Settings!C29," ",Settings!D29,"s")) | F25: =IF(Settings!L29="","",Settings!L29) | G25: =CONCATENATE(Settings!E29," ",Settings!F29) | H25: =CONCATENATE(Settings!G29," ",Settings!F29) | I25: =CONCATENATE(Settings!H29," ",Settings!F29) | J25: =CONCATENATE(Settings!I29," ",Settings!F29) | L25: =IF(Settings!M29="","",Settings!M29) | M25: =IF(Settings!N29="","",Settings!N29) | N25: =IF(CONCATENATE(Settings!J29,"-",Settings!K29) = "-","",CONCATENATE(Settings!J29,"-",Settings!K29)) | O25: =IF(Settings!O29="","",Settings!O29) | P25: =Settings!Q29 | Q25: =_xlfn.CONCAT(Settings!R29," ",Settings!F29)
... C27: =IF(Settings!A31="","",Settings!A31) | D27: =IF(Settings!B31="","",Settings!B31) | E27: =IF(CONCATENATE(Settings!C31," ",Settings!D31,"s")=" s"," ",CONCATENATE(Settings!C31," ",Settings!D31,"s")) | F27: =IF(Settings!L31="","",Settings!L31) | G27: =CONCATENATE(Settings!E31," ",Settings!F31) | H27: =CONCATENATE(Settings!G31," ",Settings!F31) | I27: =CONCATENATE(Settings!H31," ",Settings!F31) | J27: =CONCATENATE(Settings!I31," ",Settings!F31) | L27: =IF(Settings!M31="","",Settings!M31) | M27: =IF(Settings!N31="","",Settings!N31) | N27: =IF(CONCATENATE(Settings!J31,"-",Settings!K31) = "-","",CONCATENATE(Settings!J31,"-",Settings!K31)) | O27: =IF(Settings!O31="","",Settings!O31) | P27: =Settings!Q31 | Q27: =_xlfn.CONCAT(Settings!R31," ",Settings!F31)
C28: =IF(Settings!A32="","",Settings!A32) | D28: =IF(Settings!B32="","",Settings!B32) | E28: =IF(CONCATENATE(Settings!C32," ",Settings!D32,"s")=" s"," ",CONCATENATE(Settings!C32," ",Settings!D32,"s")) | F28: =IF(Settings!L32="","",Settings!L32) | G28: =CONCATENATE(Settings!E32," ",Settings!F32) | H28: =CONCATENATE(Settings!G32," ",Settings!F32) | I28: =CONCATENATE(Settings!H32," ",Settings!F32) | J28: =CONCATENATE(Settings!I32," ",Settings!F32) | N28: =IF(CONCATENATE(J80,"-",K80) = "-","",CONCATENATE(J80,"-",K80))
C29: =IF(Settings!A33="","",Settings!A33) | D29: =IF(Settings!B33="","",Settings!B33) | E29: =IF(CONCATENATE(Settings!C33," ",Settings!D33,"s")=" s"," ",CONCATENATE(Settings!C33," ",Settings!D33,"s")) | F29: =IF(Settings!L33="","",Settings!L33) | G29: =CONCATENATE(Settings!E33," ",Settings!F33) | H29: =CONCATENATE(Settings!G33," ",Settings!F33) | I29: =CONCATENATE(Settings!H33," ",Settings!F33) | J29: =CONCATENATE(Settings!I33," ",Settings!F33) | N29: =IF(CONCATENATE(J81,"-",K81) = "-","",CONCATENATE(J81,"-",K81)) | P29: Total Amount | Q29: =_xlfn.CONCAT(Settings!S18," ",Settings!F18) -> ${offerValidation.AMOUNT_IN_NUMBERS} ${table:offerProductValidation.CURRENCY}
C30: =IF(Settings!A34="","",Settings!A34) | D30: =IF(Settings!B34="","",Settings!B34) | E30: =IF(CONCATENATE(Settings!C34," ",Settings!D34,"s")=" s"," ",CONCATENATE(Settings!C34," ",Settings!D34,"s")) | F30: =IF(Settings!L34="","",Settings!L34) | G30: =CONCATENATE(Settings!E34," ",Settings!F34) | H30: =CONCATENATE(Settings!G34," ",Settings!F34) | I30: =CONCATENATE(Settings!H34," ",Settings!F34) | J30: =CONCATENATE(Settings!I34," ",Settings!F34) | N30: =IF(CONCATENATE(J82,"-",K82) = "-","",CONCATENATE(J82,"-",K82))
E31: =IF(CONCATENATE(Quotation!C83," ",Quotation!D83,"s")=" s"," ",CONCATENATE(Quotation!C83," ",Quotation!D83,"s")) | G31: =CONCATENATE(Settings!E35," ",Settings!F35) | H31: =CONCATENATE(G83," ",F83) | I31: =CONCATENATE(H83," ",F83) | J31: =CONCATENATE(I83," ",F83) | N31: =IF(CONCATENATE(J83,"-",K83) = "-","",CONCATENATE(J83,"-",K83)) | P31: VAT Amount | Q31: =_xlfn.CONCAT(Settings!T18," ",Settings!F18) -> ${offerValidation.VAT_TOTAL} ${table:offerProductValidation.CURRENCY}
E32: =IF(CONCATENATE(Quotation!C84," ",Quotation!D84,"s")=" s"," ",CONCATENATE(Quotation!C84," ",Quotation!D84,"s")) | G32: =CONCATENATE(Settings!E36," ",Settings!F36) | H32: =CONCATENATE(G84," ",F84) | I32: =CONCATENATE(H84," ",F84) | J32: =CONCATENATE(I84," ",F84) | N32: =IF(CONCATENATE(J84,"-",K84) = "-","",CONCATENATE(J84,"-",K84))
E33: =IF(CONCATENATE(Quotation!C85," ",Quotation!D85,"s")=" s"," ",CONCATENATE(Quotation!C85," ",Quotation!D85,"s")) | G33: =CONCATENATE(Settings!E37," ",Settings!F37) | H33: =CONCATENATE(G85," ",F85) | I33: =CONCATENATE(H85," ",F85) | J33: =CONCATENATE(I85," ",F85) | N33: =IF(CONCATENATE(J85,"-",K85) = "-","",CONCATENATE(J85,"-",K85)) | P33: Total Amount with VAT | Q33: =_xlfn.CONCAT(Settings!U18," ",Settings!F18) -> ${offerValidation.AMOUNT_IN_NUMBERS_VAT} ${table:offerProductValidation.CURRENCY}
E34: =IF(CONCATENATE(Quotation!C86," ",Quotation!D86,"s")=" s"," ",CONCATENATE(Quotation!C86," ",Quotation!D86,"s")) | G34: =CONCATENATE(Settings!E38," ",Settings!F38) | H34: =CONCATENATE(G86," ",F86) | I34: =CONCATENATE(H86," ",F86) | J34: =CONCATENATE(I86," ",F86)
E35: =IF(CONCATENATE(Quotation!C87," ",Quotation!D87,"s")=" s"," ",CONCATENATE(Quotation!C87," ",Quotation!D87,"s")) | H35: =CONCATENATE(G87," ",F87) | I35: =CONCATENATE(H87," ",F87)
E36: =IF(CONCATENATE(Quotation!C88," ",Quotation!D88,"s")=" s"," ",CONCATENATE(Quotation!C88," ",Quotation!D88,"s"))

Sheet Settings
A1: Header fields | B1: Description
A2: ${offerValidation.OFFERID} | B2: Contract Number
A3: ${offerValidation.TENDERID} | B3: Tender Reference
A4: ${offerValidation.OFFERDATE} | B4: Offer Date
A5: ${offerValidation.OFFERVALIDITY} | B5: Offer Validity
A6: ${offerValidation.SHIPMENTTERMS} | B6: Shipment Terms
A7: ${offerValidation.PAYMENTTERMS} | B7: Payment Terms
A8: ${offerValidation.DELIVERYTERMS} | B8: Delivery Terms
A9: ${offerValidation.INSTITUTENAME} | B9: Offer Party
A10: ${offerValidation.PROCUREMENT_REASON} | B10: Procurement reason
A16: Product table fields
A17: SKU CODE | B17: Article name | C17: PAID VOLUME | D17: UNIT | E17: OFFER PRICE | F17: CURRENCY | G17: OFFER_PRICE_VAT | H17: GROSS SALES OFFER CURRENCY | I17: GROSS_SALES_OFFER_CURRENCY_VAT | J17: OFFER_ID | K17: SORTER | L17: Pack Factor | M17: Samples | N17: Origin | O17: FOC | P17: Total Quantity Units | Q17: Total QTY | R17: Net Price | S17: Amount in numbers | T17: VAT total | U17: Amount in numbers vat
A18: ${table:offerProductValidation.SKU} | B18: ${table:offerProductValidation.PRODUCT_UNIT_NAME} | C18: ${table:offerProductValidation.PAID_VOLUME} | D18: ${table:offerProductValidation.UNIT} | E18: ${table:offerProductValidation.OFFER_PRICE} | F18: ${table:offerProductValidation.CURRENCY} | G18: ${table:offerProductValidation.OFFER_PRICE_VAT} | H18: ${table:offerProductValidation.GROSS_SALES_OFFER_CURRENCY} | I18: ${table:offerProductValidation.GROSS_SALES_OFFER_CURRENCY_VAT} | J18: ${table:offerProductValidation.OFFER_ID} | K18: ${table:offerProductValidation.SORTER} | L18: ${table:offerProductValidation.PACKSIZE} | M18: ${table:offerProductValidation.SAMPLES} | N18: ${table:offerProductValidation.COUNTRYOFORIGIN} | O18: ${table:offerProductValidation.FOC} | P18: ${table:offerProductValidation.TOTAL_QUANTITY_UNITS} | Q18: =IF(D18>0,IF(D18="Unit",CONCATENATE(Settings!P18," ",Settings!D18,"s"),CONCATENATE((Settings!P18/Settings!L18)," ",Settings!D18,"s")),"") -> #VALUE! | R18: ${table:offerProductValidation.NET_PRICE} | S18: ${offerValidation.AMOUNT_IN_NUMBERS} | T18: ${offerValidation.VAT_TOTAL} | U18: ${offerValidation.AMOUNT_IN_NUMBERS_VAT}
Q19: =IF(D19>0,IF(D19="Unit",CONCATENATE(Settings!P19," ",Settings!D19,"s"),CONCATENATE((Settings!P19/Settings!L19)," ",Settings!D19,"s")),"")
Q20: =IF(D20>0,IF(D20="Unit",CONCATENATE(Settings!P20," ",Settings!D20,"s"),CONCATENATE((Settings!P20/Settings!L20)," ",Settings!D20,"s")),"")
Q21: =IF(D21>0,IF(D21="Unit",CONCATENATE(Settings!P21," ",Settings!D21,"s"),CONCATENATE((Settings!P21/Settings!L21)," ",Settings!D21,"s")),"")
Q22: =IF(D22>0,IF(D22="Unit",CONCATENATE(Settings!P22," ",Settings!D22,"s"),CONCATENATE((Settings!P22/Settings!L22)," ",Settings!D22,"s")),"")
Q23: =IF(D23>0,IF(D23="Unit",CONCATENATE(Settings!P23," ",Settings!D23,"s"),CONCATENATE((Settings!P23/Settings!L23)," ",Settings!D23,"s")),"")
Q24: =IF(D24>0,IF(D24="Unit",CONCATENATE(Settings!P24," ",Settings!D24,"s"),CONCATENATE((Settings!P24/Settings!L24)," ",Settings!D24,"s")),"")
Q25: =IF(D25>0,IF(D25="Unit",CONCATENATE(Settings!P25," ",Settings!D25,"s"),CONCATENATE((Settings!P25/Settings!L25)," ",Settings!D25,"s")),"")
Q26: =IF(D26>0,IF(D26="Unit",CONCATENATE(Settings!P26," ",Settings!D26,"s"),CONCATENATE((Settings!P26/Settings!L26)," ",Settings!D26,"s")),"")
Q27: =IF(D27>0,IF(D27="Unit",CONCATENATE(Settings!P27," ",Settings!D27,"s"),CONCATENATE((Settings!P27/Settings!L27)," ",Settings!D27,"s")),"")
Q28: =IF(D28>0,IF(D28="Unit",CONCATENATE(Settings!P28," ",Settings!D28,"s"),CONCATENATE((Settings!P28/Settings!L28)," ",Settings!D28,"s")),"")
Q29: =IF(D29>0,IF(D29="Unit",CONCATENATE(Settings!P29," ",Settings!D29,"s"),CONCATENATE((Settings!P29/Settings!L29)," ",Settings!D29,"s")),"")
Q30: =IF(D30>0,IF(D30="Unit",CONCATENATE(Settings!P30," ",Settings!D30,"s"),CONCATENATE((Settings!P30/Settings!L30)," ",Settings!D30,"s")),"")
... Q52: =IF(D52>0,IF(D52="Unit",CONCATENATE(Settings!P52," ",Settings!D52,"s"),CONCATENATE((Settings!P52/Settings!L52)," ",Settings!D52,"s")),"")
