Workbook

Sheet Quotation
C3: Offer Party | D3: ${offerValidation.INSTITUTENAME}
C5: Procurement Method | D5: !!! Missing from OfferValidation !!! | E5: In page: {fastAppData>/EditTender/PROCUREMENT_METHOD_ID} {fastAppData>/EditTender/PROCUREMENT_REASON}
C7: Contract Number | F7: Tender Reference | I7: Offer Date | L7: Offer Validity
C8: =Settings!A2 -> ${offerValidation.OFFERID} | F8: =Settings!A3 -> ${offerValidation.TENDERID} | I8: =Settings!A4 -> ${offerValidation.OFFERDATE} | L8: =Settings!A5 -> ${offerValidation.OFFERVALIDITY}
C10: Shipment Terms | F10: Payment Terms | I10: Delivery Terms
C11: =Settings!A6 -> ${offerValidation.SHIPMENTTERMS} | F11: =Settings!A7 -> ${offerValidation.PAYMENTTERMS} | I11: =Settings!A8 -> ${offerValidation.DELIVERYTERMS}
D13: Article Name | E13: Qty | F13: Pack Factor | G13: MSP | H13: MSP with VAT | I13: Total | J13: Total with VAT | L13: Samples | M13: Origin | N13: Contract ID | O13: FOC | P13: Total Qty | Q13: NSP
C14: =Settings!A18 -> ${table:offerProductValidation.SKU} | D14: =Settings!B18 -> ${table:offerProductValidation.PRODUCT_UNIT_NAME} | E14: =IF(CONCATENATE(Settings!C18," ",Settings!D18,"s")=" s"," ",CONCATENATE(Settings!C18," ",Settings!D18,"s")) -> ${table:offerProductValidation.PAID_VOLUME} ${table:offerProductValidation.UNIT}s | F14: =Settings!L18 -> ${table:offerProductValidation.PACKSIZE} | G14: =CONCATENATE(Settings!E18," ",Settings!F18) -> ${table:offerProductValidation.OFFER_PRICE} ${table:offerProductValidation.CURRENCY} | H14: =CONCATENATE(Settings!G18," ",Settings!F18) -> ${table:offerProductValidation.OFFER_PRICE_VAT} ${table:offerProductValidation.CURRENCY} | I14: =CONCATENATE(Settings!H18," ",Settings!F18) -> ${table:offerProductValidation.GROSS_SALES_OFFER_CURRENCY} ${table:offerProductValidation.CURRENCY} | J14: =CONCATENATE(Settings!I18," ",Settings!F18) -> ${table:offerProductValidation.GROSS_SALES_OFFER_CURRENCY_VAT} ${table:offerProductValidation.CURRENCY} | L14: =Settings!M18 -> ${table:offerProductValidation.SAMPLES} | M14: =Settings!N18 -> ${table:offerProductValidation.COUNTRYOFORIGIN} | N14: =IF(CONCATENATE(Settings!J18,"-",Settings!K18) = "-","",CONCATENATE(Settings!J18,"-",Settings!K18)) -> ${table:offerProductValidation.OFFER_ID}-${table:offerProductValidation.SORTER} | O14: =Settings!O18 -> ${table:offerProductValidation.FOC} | P14: ${table:offerProductValidation.UNIT === 'Unit' ? offerProductValidation.TOTAL_QUANTITY_UNITS + ' ' + offerProductValidation.UNIT + 's' : (offerProductValidation.TOTAL_QUANTITY_UNITS / offerProductValidation.PACKSIZE) + ' ' + offerProductValidation.UNIT + 's'} | Q14: ${table:offerProductValidation.NET_PRICE + ' ' + offerProductValidation.CURRENCY}
E15: =IF(CONCATENATE(Quotation!C67," ",Quotation!D67,"s")=" s"," ",CONCATENATE(Quotation!C67," ",Quotation!D67,"s")) | G15: =CONCATENATE(E67," ",F67) | H15: =CONCATENATE(G67," ",F67) | I15: =CONCATENATE(H67," ",F67) | J15: =CONCATENATE(I67," ",F67) | N15: =IF(CONCATENATE(J67,"-",K67) = "-","",CONCATENATE(J67,"-",K67))
E16: =IF(CONCATENATE(Quotation!C68," ",Quotation!D68,"s")=" s"," ",CONCATENATE(Quotation!C68," ",Quotation!D68,"s")) | G16: =CONCATENATE(E68," ",F68) | H16: =CONCATENATE(G68," ",F68) | I16: =CONCATENATE(H68," ",F68) | J16: =CONCATENATE(I68," ",F68) | N16: =IF(CONCATENATE(J68,"-",K68) = "-","",CONCATENATE(J68,"-",K68)) | P16: Total Amount | Q16: ${offerValidation.AMOUNT_IN_NUMBERS + ' ' + offerValidation.CURRENCY}
E17: =IF(CONCATENATE(Quotation!C69," ",Quotation!D69,"s")=" s"," ",CONCATENATE(Quotation!C69," ",Quotation!D69,"s")) | G17: =CONCATENATE(E69," ",F69) | H17: =CONCATENATE(G69," ",F69) | I17: =CONCATENATE(H69," ",F69) | J17: =CONCATENATE(I69," ",F69) | N17: =IF(CONCATENATE(J69,"-",K69) = "-","",CONCATENATE(J69,"-",K69))
E18: =IF(CONCATENATE(Quotation!C70," ",Quotation!D70,"s")=" s"," ",CONCATENATE(Quotation!C70," ",Quotation!D70,"s")) | G18: =CONCATENATE(E70," ",F70) | H18: =CONCATENATE(G70," ",F70) | I18: =CONCATENATE(H70," ",F70) | J18: =CONCATENATE(I70," ",F70) | N18: =IF(CONCATENATE(J70,"-",K70) = "-","",CONCATENATE(J70,"-",K70)) | P18: VAT Amount | Q18: ${offerValidation.VAT_TOTAL + ' ' + offerValidation.CURRENCY}
E19: =IF(CONCATENATE(Quotation!C71," ",Quotation!D71,"s")=" s"," ",CONCATENATE(Quotation!C71," ",Quotation!D71,"s")) | G19: =CONCATENATE(E71," ",F71) | H19: =CONCATENATE(G71," ",F71) | I19: =CONCATENATE(H71," ",F71) | J19: =CONCATENATE(I71," ",F71) | N19: =IF(CONCATENATE(J71,"-",K71) = "-","",CONCATENATE(J71,"-",K71))
E20: =IF(CONCATENATE(Quotation!C72," ",Quotation!D72,"s")=" s"," ",CONCATENATE(Quotation!C72," ",Quotation!D72,"s")) | G20: =CONCATENATE(E72," ",F72) | H20: =CONCATENATE(G72," ",F72) | I20: =CONCATENATE(H72," ",F72) | J20: =CONCATENATE(I72," ",F72) | N20: =IF(CONCATENATE(J72,"-",K72) = "-","",CONCATENATE(J72,"-",K72)) | P20: Total Amount with VAT | Q20: ${offerValidation.AMOUNT_IN_NUMBERS_VAT + ' ' + offerValidation.CURRENCY}
E21: =IF(CONCATENATE(Quotation!C73," ",Quotation!D73,"s")=" s"," ",CONCATENATE(Quotation!C73," ",Quotation!D73,"s")) | G21: =CONCATENATE(E73," ",F73) | H21: =CONCATENATE(G73," ",F73) | I21: =CONCATENATE(H73," ",F73) | J21: =CONCATENATE(I73," ",F73) | N21: =IF(CONCATENATE(J73,"-",K73) = "-","",CONCATENATE(J73,"-",K73))
E22: =IF(CONCATENATE(Quotation!C74," ",Quotation!D74,"s")=" s"," ",CONCATENATE(Quotation!C74," ",Quotation!D74,"s")) | G22: =CONCATENATE(E74," ",F74) | H22: =CONCATENATE(G74," ",F74) | I22: =CONCATENATE(H74," ",F74) | J22: =CONCATENATE(I74," ",F74) | N22: =IF(CONCATENATE(J74,"-",K74) = "-","",CONCATENATE(J74,"-",K74))
E23: =IF(CONCATENATE(Quotation!C75," ",Quotation!D75,"s")=" s"," ",CONCATENATE(Quotation!C75," ",Quotation!D75,"s")) | G23: =CONCATENATE(E75," ",F75) | H23: =CONCATENATE(G75," ",F75) | I23: =CONCATENATE(H75," ",F75) | J23: =CONCATENATE(I75," ",F75) | N23: =IF(CONCATENATE(J75,"-",K75) = "-","",CONCATENATE(J75,"-",K75))
E24: =IF(CONCATENATE(Quotation!C76," ",Quotation!D76,"s")=" s"," ",CONCATENATE(Quotation!C76," ",Quotation!D76,"s")) | G24: =CONCATENATE(E76," ",F76) | H24: =CONCATENATE(G76," ",F76) | I24: =CONCATENATE(H76," ",F76) | J24: =CONCATENATE(I76," ",F76) | N24: =IF(CONCATENATE(J76,"-",K76) = "-","",CONCATENATE(J76,"-",K76))
E25: =IF(CONCATENATE(Quotation!C77," ",Quotation!D77,"s")=" s"," ",CONCATENATE(Quotation!C77," ",Quotation!D77,"s")) | G25: =CONCATENATE(E77," ",F77) | H25: =CONCATENATE(G77," ",F77) | I25: =CONCATENATE(H77," ",F77) | J25: =CONCATENATE(I77," ",F77) | N25: =IF(CONCATENATE(J77,"-",K77) = "-","",CONCATENATE(J77,"-",K77))
E26: =IF(CONCATENATE(Quotation!C78," ",Quotation!D78,"s")=" s"," ",CONCATENATE(Quotation!C78," ",Quotation!D78,"s")) | G26: =CONCATENATE(E78," ",F78) | H26: =CONCATENATE(G78," ",F78) | I26: =CONCATENATE(H78," ",F78) | J26: =CONCATENATE(I78," ",F78) | N26: =IF(CONCATENATE(J78,"-",K78) = "-","",CONCATENATE(J78,"-",K78))
E27: =IF(CONCATENATE(Quotation!C79," ",Quotation!D79,"s")=" s"," ",CONCATENATE(Quotation!C79," ",Quotation!D79,"s")) | G27: =CONCATENATE(E79," ",F79) | H27: =CONCATENATE(G79," ",F79) | I27: =CONCATENATE(H79," ",F79) | J27: =CONCATENATE(I79," ",F79) | N27: =IF(CONCATENATE(J79,"-",K79) = "-","",CONCATENATE(J79,"-",K79))
E28: =IF(CONCATENATE(Quotation!C80," ",Quotation!D80,"s")=" s"," ",CONCATENATE(Quotation!C80," ",Quotation!D80,"s")) | G28: =CONCATENATE(E80," ",F80) | H28: =CONCATENATE(G80," ",F80) | I28: =CONCATENATE(H80," ",F80) | J28: =CONCATENATE(I80," ",F80) | N28: =IF(CONCATENATE(J80,"-",K80) = "-","",CONCATENATE(J80,"-",K80))
E29: =IF(CONCATENATE(Quotation!C81," ",Quotation!D81,"s")=" s"," ",CONCATENATE(Quotation!C81," ",Quotation!D81,"s")) | G29: =CONCATENATE(E81," ",F81) | H29: =CONCATENATE(G81," ",F81) | I29: =CONCATENATE(H81," ",F81) | J29: =CONCATENATE(I81," ",F81) | N29: =IF(CONCATENATE(J81,"-",K81) = "-","",CONCATENATE(J81,"-",K81))
E30: =IF(CONCATENATE(Quotation!C82," ",Quotation!D82,"s")=" s"," ",CONCATENATE(Quotation!C82," ",Quotation!D82,"s")) | G30: =CONCATENATE(E82," ",F82) | H30: =CONCATENATE(G82," ",F82) | I30: =CONCATENATE(H82," ",F82) | J30: =CONCATENATE(I82," ",F82) | N30: =IF(CONCATENATE(J82,"-",K82) = "-","",CONCATENATE(J82,"-",K82))
E31: =IF(CONCATENATE(Quotation!C83," ",Quotation!D83,"s")=" s"," ",CONCATENATE(Quotation!C83," ",Quotation!D83,"s")) | G31: =CONCATENATE(E83," ",F83) | H31: =CONCATENATE(G83," ",F83) | I31: =CONCATENATE(H83," ",F83) | J31: =CONCATENATE(I83," ",F83) | N31: =IF(CONCATENATE(J83,"-",K83) = "-","",CONCATENATE(J83,"-",K83))
E32: =IF(CONCATENATE(Quotation!C84," ",Quotation!D84,"s")=" s"," ",CONCATENATE(Quotation!C84," ",Quotation!D84,"s")) | G32: =CONCATENATE(E84," ",F84) | H32: =CONCATENATE(G84," ",F84) | I32: =CONCATENATE(H84," ",F84) | J32: =CONCATENATE(I84," ",F84) | N32: =IF(CONCATENATE(J84,"-",K84) = "-","",CONCATENATE(J84,"-",K84))
E33: =IF(CONCATENATE(Quotation!C85," ",Quotation!D85,"s")=" s"," ",CONCATENATE(Quotation!C85," ",Quotation!D85,"s")) | G33: =CONCATENATE(E85," ",F85) | H33: =CONCATENATE(G85," ",F85) | I33: =CONCATENATE(H85," ",F85) | J33: =CONCATENATE(I85," ",F85) | N33: =IF(CONCATENATE(J85,"-",K85) = "-","",CONCATENATE(J85,"-",K85))
E34: =IF(CONCATENATE(Quotation!C86," ",Quotation!D86,"s")=" s"," ",CONCATENATE(Quotation!C86," ",Quotation!D86,"s")) | G34: =CONCATENATE(E86," ",F86) | H34: =CONCATENATE(G86," ",F86) | I34: =CONCATENATE(H86," ",F86) | J34: =CONCATENATE(I86," ",F86)
E35: =IF(CONCATENATE(Quotation!C87," ",Quotation!D87,"s")=" s"," ",CONCATENATE(Quotation!C87," ",Quotation!D87,"s")) | H35: =CONCATENATE(G87," ",F87) | I35: =CONCATENATE(H87," ",F87)
E36: =IF(CONCATENATE(Quotation!C88," ",Quotation!D88,"s")=" s"," ",CONCATENATE(Quotation!C88," ",Quotation!D88,"s"))

Sheet Settings
A1: Header fields | B1: Description
A2: ${offerValidation.OFFERID} | B2: Contract Number
A3: ${offerValidation.TENDERID} | B3: Tender Reference
A4: ${offerValidation.OFFERDATE} | B4: Offer Date
A5: ${offerValidation.OFFERVALIDITY} | B5: Offer Validity
A6: ${offerValidation.SHIPMENTTERMS} | B6: Shipment Terms
A7: ${offerValidation.PAYMENTTERMS} | B7: Payment Terms
A8: ${offerValidation.DELIVERYTERMS} | B8: Delivery Terms
A16: Product table fields
A17: SKU CODE | B17: Article name | C17: PAID VOLUME | D17: UNIT | E17: OFFER PRICE | F17: CURRENCY | G17: OFFER_PRICE_VAT | H17: GROSS SALES OFFER CURRENCY | I17: GROSS_SALES_OFFER_CURRENCY_VAT | J17: OFFER_ID | K17: SORTER | L17: Pack Factor | M17: Samples | N17: Origin | O17: FOC | P17: Total Quantity Units | Q17: Kolom2 | R17: Kolom3 | S17: Kolom4 | T17: Kolom5 | U17: Kolom6
A18: ${table:offerProductValidation.SKU} | B18: ${table:offerProductValidation.PRODUCT_UNIT_NAME} | C18: ${table:offerProductValidation.PAID_VOLUME} | D18: ${table:offerProductValidation.UNIT} | E18: ${table:offerProductValidation.OFFER_PRICE} | F18: ${table:offerProductValidation.CURRENCY} | G18: ${table:offerProductValidation.OFFER_PRICE_VAT} | H18: ${table:offerProductValidation.GROSS_SALES_OFFER_CURRENCY} | I18: ${table:offerProductValidation.GROSS_SALES_OFFER_CURRENCY_VAT} | J18: ${table:offerProductValidation.OFFER_ID} | K18: ${table:offerProductValidation.SORTER} | L18: ${table:offerProductValidation.PACKSIZE} | M18: ${table:offerProductValidation.SAMPLES} | N18: ${table:offerProductValidation.COUNTRYOFORIGIN} | O18: ${table:offerProductValidation.FOC} | P18: ${offerProductValidation.TOTAL_QUANTITY_UNITS}
